cbwheelziptest/__init__.py
cbwheelziptest-0.0.2.dist-info/WHEEL
cbwheelziptest-0.0.2.dist-info/METADATA
cbwheelziptest-0.0.2.dist-info/RECORD
