Metadata-Version: 2.4
Name: cbwheelziptest
Version: 0.0.2
Summary: A mysterious example Python package!
Author-email: Caleb <calebbrown@google.com>
Requires-Dist: requests
